rtl/sequential/d_flipflop.sv
module d_flipflop(
    input logic clk,
    input logic d,
    output logic q
);

always_ff @(posedge clk) begin
    q<=d;
end
endmodule

tb/sequential/d_flipflop_tb.sv
module d_flipflop_tb;
logic clk;
initial clk = 0;
always #5 clk = ~clk;
logic d;
logic q;

d_flipflop d_ff_uut(
    .clk(clk),
    .d(d),
    .q(q)
);

initial begin
$dumpfile("d_flipflop.vcd");
$dumpvars(0, d_flipflop_tb);
$monitor("time=%0t clk=%b d=%b q=%b", $time, clk, d, q);
d=0; #20;
d=1; #20;
d=0; #10;
d=1; #20;
$finish;
end
endmodule

code/verilog/Day010/d_flipflop.vcd
$date
	Tue May 12 15:10:43 2026
$end
$version
	Icarus Verilog
$end
$timescale
	1s
$end
$scope module d_flipflop_tb $end
$var wire 1 ! q $end
$var reg 1 " clk $end
$var reg 1 # d $end
$scope module d_ff_uut $end
$var wire 1 " clk $end
$var wire 1 # d $end
$var reg 1 ! q $end
$upscope $end
$upscope $end
$enddefinitions $end
#0
$dumpvars
0#
0"
x!
$end
#5
0!
1"
#10
0"
#15
1"
#20
0"
1#
#25
1!
1"
#30
0"
#35
1"
#40
0"
0#
#45
0!
1"
#50
0"
1#
#55
1!
1"
