rtl/sequential/counter_4bit.sv
module counter_4bit(
    input logic clk,
    input logic rst_n,
    input logic enable,
    output logic [3:0] count
);

always_ff @(posedge clk) begin
    if (!rst_n) begin
        count <= 0;
    end 
    else if (enable) begin
        count <= count + 1;
    end
end
endmodule

code/verilog/Day011/counter_4bit_tb.sv
module counter_4bit_tb;
logic clk;
initial clk = 0;
always #5 clk = ~clk;
logic rst_n;
logic enable;
logic [3:0] count;

counter_4bit couter4_uut(
    .clk(clk),
    .rst_n(rst_n),
    .enable(enable),
    .count(count)
);

initial begin 
$dumpfile("counter_4bit.vcd");
$dumpvars(0, counter_4bit_tb);
$monitor("time=%0t clk=%b rst_n=%b enable=%b count=%b", $time, clk, rst_n, enable, count);

rst_n=0; enable=1; #10;

rst_n=1; enable=1; #20;
rst_n=1; enable=0; #10;
if (count != 4'b0010) begin
    $display("FAIL, Hold check");
end else begin
    $display("PASS, Hold check");
end

rst_n=0; enable=1; #10;
if (count != 4'b0000) begin
    $display("FAIL, reset check");
end else begin
    $display("PASS, reset check");
end

rst_n=1; enable=1; #160;
if (count != 4'b0000) begin
    $display("FAIL, wraparound check");
end else begin
    $display("PASS, wraparound check");
end

$finish;
end
endmodule

sim/sequential/counter_4bit.vcd
$date
	Wed May 13 13:02:50 2026
$end
$version
	Icarus Verilog
$end
$timescale
	1s
$end
$scope module counter_4bit_tb $end
$var wire 4 ! count [3:0] $end
$var reg 1 " clk $end
$var reg 1 # enable $end
$var reg 1 $ rst_n $end
$scope module couter4_uut $end
$var wire 1 " clk $end
$var wire 1 # enable $end
$var wire 1 $ rst_n $end
$var reg 4 % count [3:0] $end
$upscope $end
$upscope $end
$enddefinitions $end
#0
$dumpvars
bx %
0$
1#
0"
bx !
$end
#5
b0 !
b0 %
1"
#10
0"
1$
#15
b1 !
b1 %
1"
#20
0"
#25
b10 !
b10 %
1"
#30
0"
0#
#35
1"
#40
0"
1#
0$
#45
b0 !
b0 %
1"
#50
0"
1$
#55
b1 !
b1 %
1"
#60
0"
#65
b10 !
b10 %
1"
#70
0"
#75
b11 !
b11 %
1"
#80
0"
#85
b100 !
b100 %
1"
#90
0"
#95
b101 !
b101 %
1"
#100
0"
#105
b110 !
b110 %
1"
#110
0"
#115
b111 !
b111 %
1"
#120
0"
#125
b1000 !
b1000 %
1"
#130
0"
#135
b1001 !
b1001 %
1"
#140
0"
#145
b1010 !
b1010 %
1"
#150
0"
#155
b1011 !
b1011 %
1"
#160
0"
#165
b1100 !
b1100 %
1"
#170
0"
#175
b1101 !
b1101 %
1"
#180
0"
#185
b1110 !
b1110 %
1"
#190
0"
#195
b1111 !
b1111 %
1"
#200
0"
#205
b0 !
b0 %
1"
