rtl/sequential/counter_4bit.sv
module counter_4bit(
    input logic clk,
    input logic rst_n,
    input logic enable,
    output logic [3:0] count
);

always_ff @(posedge clk) begin
    if (!rst_n) begin
        count <= 0;
    end 
    else if (enable) begin
        count <= count + 1;
    end
end
endmodule

code/verilog/Day012/counter_4bit_tb.sv
module counter_4bit_tb;
logic clk;
initial clk=0;
always #5 clk = ~clk;
logic rst_n;
logic enable;
logic [3:0] count;

counter_4bit counter_uut (
    .clk(clk),
    .rst_n(rst_n),
    .enable(enable),
    .count(count)
);

//function like C
task tick(input int n);
begin
    repeat(n) @(posedge clk);
    #1;
end
endtask

initial begin
$dumpfile("counter_4bit.vcd");
$dumpvars(0, counter_4bit_tb);
$monitor("time=%0t clk=%b rst_n=%b enable=%b count=%b", $time, clk, rst_n, enable, count);
rst_n=0; enable=1;
tick(2);

rst_n=1; enable=1;
tick(2);
assert(count == 4'b0010) 
    else $fatal(1, "increment fail");
$display("increment pass");

//hold check
enable=0;
tick(1);
assert(count == 4'b0010) 
    else $fatal(1, "hold fail");
$display("hold pass");

//reset
rst_n=0;
tick(1);
assert(count == 4'b0000) 
    else $fatal(1, "reset fail");
$display("reset pass");

//wraparound
rst_n=1; enable=1;
tick(16);
assert(count == 4'b0000) 
    else $fatal(1, "wraparound fail");
$display("wraparound pass");

$finish;
end
endmodule

sim/sequential/counter_4bit_v2.vcd
$date
	Thu May 14 18:19:53 2026
$end
$version
	Icarus Verilog
$end
$timescale
	1s
$end
$scope module counter_4bit_tb $end
$var wire 4 ! count [3:0] $end
$var reg 1 " clk $end
$var reg 1 # enable $end
$var reg 1 $ rst_n $end
$scope module counter_uut $end
$var wire 1 " clk $end
$var wire 1 # enable $end
$var wire 1 $ rst_n $end
$var reg 4 % count [3:0] $end
$upscope $end
$scope task tick $end
$var integer 32 & n [31:0] $end
$upscope $end
$upscope $end
$enddefinitions $end
#0
$dumpvars
b10 &
bx %
0$
1#
0"
bx !
$end
#5
b0 !
b0 %
1"
#10
0"
#15
1"
#16
1$
#20
0"
#25
b1 !
b1 %
1"
#30
0"
#35
b10 !
b10 %
1"
#36
b1 &
0#
#40
0"
#45
1"
#46
0$
#50
0"
#55
b0 !
b0 %
1"
#56
b10000 &
1#
1$
#60
0"
#65
b1 !
b1 %
1"
#70
0"
#75
b10 !
b10 %
1"
#80
0"
#85
b11 !
b11 %
1"
#90
0"
#95
b100 !
b100 %
1"
#100
0"
#105
b101 !
b101 %
1"
#110
0"
#115
b110 !
b110 %
1"
#120
0"
#125
b111 !
b111 %
1"
#130
0"
#135
b1000 !
b1000 %
1"
#140
0"
#145
b1001 !
b1001 %
1"
#150
0"
#155
b1010 !
b1010 %
1"
#160
0"
#165
b1011 !
b1011 %
1"
#170
0"
#175
b1100 !
b1100 %
1"
#180
0"
#185
b1101 !
b1101 %
1"
#190
0"
#195
b1110 !
b1110 %
1"
#200
0"
#205
b1111 !
b1111 %
1"
#210
0"
#215
b0 !
b0 %
1"
