rtl/sequential/register_4bit.sv
module register_4bit(
    input logic clk,
    input logic write_enable,
    input logic [3:0] d,
    output logic [3:0] q
);

always_ff @(posedge clk) begin
    if (write_enable) begin
        q <= d;
    end
end
endmodule

code/verilog/Day011/register_4bit_tb.sv
module register_4bit_tb;
logic clk;
initial clk = 0;
always #5 clk = ~clk;
logic write_enable;
logic [3:0] d;
logic [3:0] q;

register_4bit reg_4bit_uut(
    .clk(clk),
    .write_enable(write_enable),
    .d(d),
    .q(q)
);

initial begin
$dumpfile("register_4bit.vcd");
$dumpvars(0, register_4bit_tb);
$monitor("time=%0t clk=%b write_enable=%b d=%b q=%b", $time, clk, write_enable, d, q);
write_enable=1; d=4'b1101; #10;
write_enable=0; d=4'b1010; #10;
write_enable=1; d=4'b1110; #10;
write_enable=1; d=4'b1010; #10; 
write_enable=0; d=4'b1111; #10;  
write_enable=0; d=4'b0000; #10;  
write_enable=1; d=4'b0110; #10;  
$finish;
end
endmodule

sim/sequential/register_4bit.vcd
$date
	Wed May 13 12:15:36 2026
$end
$version
	Icarus Verilog
$end
$timescale
	1s
$end
$scope module register_4bit_tb $end
$var wire 4 ! q [3:0] $end
$var reg 1 " clk $end
$var reg 4 # d [3:0] $end
$var reg 1 $ write_enable $end
$scope module reg_4bit_uut $end
$var wire 1 " clk $end
$var wire 4 % d [3:0] $end
$var wire 1 $ write_enable $end
$var reg 4 & q [3:0] $end
$upscope $end
$upscope $end
$enddefinitions $end
#0
$dumpvars
bx &
b1101 %
1$
b1101 #
0"
bx !
$end
#5
b1101 !
b1101 &
1"
#10
0"
b1010 #
b1010 %
0$
#15
1"
#20
0"
b1110 #
b1110 %
1$
#25
b1110 !
b1110 &
1"
#30
0"
b1010 #
b1010 %
#35
b1010 !
b1010 &
1"
#40
0"
b1111 #
b1111 %
0$
#45
1"
#50
0"
b0 #
b0 %
#55
1"
#60
0"
b110 #
b110 %
1$
#65
b110 !
b110 &
1"
